CHANGES.txt
MANIFEST.in
README.md
setup.py
pyramid_avro/__init__.py
pyramid_avro/decorators.py
pyramid_avro/py2_compat.py
pyramid_avro/routes.py
pyramid_avro/settings.py
pyramid_avro/utils.py
pyramid_avro/version.py
pyramid_avro.egg-info/PKG-INFO
pyramid_avro.egg-info/SOURCES.txt
pyramid_avro.egg-info/dependency_links.txt
pyramid_avro.egg-info/not-zip-safe
pyramid_avro.egg-info/requires.txt
pyramid_avro.egg-info/top_level.txt
requirements/main.txt
requirements/test.txt