Metadata-Version: 1.1
Name: pyramid-avro
Version: 0.1.0
Summary: Avro RPC Bindings for Pyramid
Home-page: http://github.com/packagelib/pyramid-avro
Author: Alex Milstead
Author-email: alex@amilstead.com
License: Apache License (2.0)
Keywords: pyramid avro
Platform: UNKNOWN
Classifier: Programming Language :: Python
Classifier: Framework :: Pyramid
Classifier: Topic :: Internet :: WWW/HTTP
Classifier: Topic :: Internet :: WWW/HTTP :: WSGI :: Application
